{"httpProtocol":"HTTP/1.1","clientAcceptEncoding":"gzip, deflate, br","requestPriority":"","edgeRequestKeepAliveStatus":1,"requestHeaderNames":{},"clientTcpRtt":26,"colo":"LHR","asn":15704,"asOrganization":"Xtra Telecom S.A.","country":"ES","isEUCountry":"1","city":"Barcelona","continent":"EU","region":"Catalonia","regionCode":"CT","timezone":"Europe/Madrid","longitude":"2.15899","latitude":"41.38879","postalCode":"08007","tlsVersion":"TLSv1.3","tlsCipher":"AEAD-AES256-GCM-SHA384","tlsClientRandom":"AlITmHGXRijF022jLsYKGsVtGci42RJwlYaqjsEkQtc=","tlsClientCiphersSha1":"kXrN3VEKDdzz2cPKTQaKzpxVTxQ=","tlsClientExtensionsSha1":"1eY97BUYYO8vDaTfHQywB1pcNdM=","tlsClientExtensionsSha1Le":"u4wtEMFQBY18l3BzHAvORm+KGRw=","tlsExportedAuthenticator":{"clientHandshake":"e9995f7b2d42661e0e810d2637b110f869aa6ded57a99e179e95aa9d433b4afa694bb52854cd09176835124dbf30cb9c","serverHandshake":"21d3ecefa7c0511be98321ede3c90b9778b3446f80771727c33373b8137d1fb909cee07ee94185bb13ad55a4a37dee64","clientFinished":"ce346a7e7b30331eb4a3bfc211b009fa9074fcf2b91dbf9f40dee84bee91bce4b8f63d5c0f4239379918f69526a1f033","serverFinished":"fa2cb9ca5494a9ce2f10eefb67acd139b86ad82f0a2452a3a1b7789d813023088bef9d59a9ce6bc84e03b6c940e445cf"},"tlsClientHelloLength":"1605","tlsClientAuth":{"certPresented":"0","certVerified":"NONE","certRevoked":"0","certIssuerDN":"","certSubjectDN":"","certIssuerDNRFC2253":"","certSubjectDNRFC2253":"","certIssuerDNLegacy":"","certSubjectDNLegacy":"","certSerial":"","certIssuerSerial":"","certSKI":"","certIssuerSKI":"","certFingerprintSHA1":"","certFingerprintSHA256":"","certNotBefore":"","certNotAfter":""},"verifiedBotCategory":"","botManagement":{"corporateProxy":false,"verifiedBot":false,"jsDetection":{"passed":false},"staticResource":false,"detectionIds":{},"score":99}}